fast_dot/__init__.py
fast_dot/fast_dot.cpython-311-x86_64-linux-gnu.so
fastdotrs-0.1.3.dist-info/METADATA
fastdotrs-0.1.3.dist-info/WHEEL
fastdotrs-0.1.3.dist-info/RECORD
