Metadata-Version: 2.4
Name: fastdotrs
Version: 0.1.3
Classifier: Programming Language :: Python
Classifier: Programming Language :: Rust
Classifier: Topic :: Scientific/Engineering :: Artificial Intelligence
Summary: Fast SIMD-optimized dot products (f32·f32, f16·f32)
Author: Coda Research Group
License: MIT OR Apache-2.0
Requires-Python: >=3.8
